{
  "deliveryOrders": [
    {
      "id": "1",
      "quantity": "2",
      "amount": "240",
      "date": "23-07-2020",
      "location": {
        "lat": "77.67",
        "lng": "121.99"
      },
      "address": "#702, sector 7, Kurukshetra",
      "status": "confirmed"
    }
  ], 
  
  "signup": {
  "full_name": "Ricky Chouhan",
  "phone_number": "9876543210",
  "address": "#702, sector 7, Kurukshetra",
  "location": {
    "lat": "72.77",
    "lng": "121.88"
  },
  "pin_code": "136038"
},
  
 "createOrder": {
  "quantity": "2",
  "amount": "240"
},
  
"eggsPrice":{
  "price": "90"
},
  
"myOrders": [
    {
      "quantity": "2",
      "amount": "240",
      "date": "23-07-2020",
      "status": "delivered"
    }
  ]
}
